Metadata-Version: 2.1
Name: colabcode-domain
Version: 0.3.2
Summary: ColabCode - Run codeserver on Colab with custom domain on Ngrok!
Home-page: https://github.com/abhishekkrthakur/colabcode
Author: Raymondt
Author-email: raymondt0809@gmail.com
License: MIT License
Platform: linux
Platform: unix
Requires-Python: >3.5.2
License-File: LICENSE
